{
  "strategy_name": "abbas",
  "params": {
    "roi": {
      "200": 0
    },
    "stoploss": {
      "stoploss": -0.04
    },
    "trailing": {
      "trailing_stop": true,
      "trailing_stop_positive": 0.0003,
      "trailing_stop_positive_offset": 0.0106,
      "trailing_only_offset_is_reached": true
    },
    "buy": {
      "base_nb_candles_buy": 30,
      "ewo_high": 2.025,
      "ewo_high_2": -3.38,
      "ewo_low": -10.92,
      "low_offset": 1.008,
      "low_offset_2": 0.94,
      "min_profit": 1.04,
      "rsi_buy": 58
    },
    "sell": {
      "base_nb_candles_sell": 8,
      "high_offset": 1.037,
      "high_offset_2": 1.403,
      "high_offset_ema": 0.93
    },
    "protection": {
      "cooldown_stop_duration_candles": 2,
      "lowprofit_lookback_period_candles": 20,
      "lowprofit_required_profit": 0.024,
      "lowprofit_stop_duration_candles": 91,
      "lowprofit_trade_limit": 29,
      "maxdrawdown_lookback_period_candles": 36,
      "maxdrawdown_max_allowed_drawdown": 0.2,
      "maxdrawdown_stop_duration_candles": 43,
      "maxdrawdown_trade_limit": 16,
      "stoplossguard_lookback_period_candles": 33,
      "stoplossguard_stop_duration_candles": 13,
      "stoplossguard_trade_limit": 14
    }
  },
  "ft_stratparam_v": 1,
  "export_time": "2022-05-08 14:52:16.650098+00:00"
}